digichem/__init__.py
digichem/basis.py
digichem/datas.py
digichem/log.py
digichem/memory.py
digichem/translate.py
digichem/config/README
digichem/config/__init__.py
digichem/config/base.py
digichem/config/locations.py
digichem/config/parse.py
digichem/config/util.py
digichem/data/README
digichem/data/functionals.csv
digichem/data/solvents.csv
digichem/data/batoms/COPYING
digichem/data/batoms/LICENSE
digichem/data/batoms/README
digichem/data/batoms/__init__.py
digichem/data/batoms/batoms-renderer.py
digichem/data/batoms/batoms_renderer.py
digichem/data/config/digichem.yaml
digichem/data/tachyon/COPYING.md
digichem/data/tachyon/LICENSE
digichem/data/tachyon/tachyon_LINUXAMD64
digichem/data/vmd/common.tcl
digichem/data/vmd/generate_combined_orbital_images.tcl
digichem/data/vmd/generate_density_images.tcl
digichem/data/vmd/generate_dipole_images.tcl
digichem/data/vmd/generate_orbital_images.tcl
digichem/data/vmd/generate_spin_images.tcl
digichem/data/vmd/generate_structure_images.tcl
digichem/exception/__init__.py
digichem/exception/base.py
digichem/exception/uncatchable.py
digichem/file/__init__.py
digichem/file/base.py
digichem/file/cube.py
digichem/file/fchk.py
digichem/file/prattle.py
digichem/file/types.py
digichem/image/__init__.py
digichem/image/base.py
digichem/image/excited_states.py
digichem/image/graph.py
digichem/image/orbitals.py
digichem/image/render.py
digichem/image/spectroscopy.py
digichem/image/structure.py
digichem/image/vmd.py
digichem/input/__init__.py
digichem/input/base.py
digichem/input/digichem_input.py
digichem/input/gaussian.py
digichem/misc/__init__.py
digichem/misc/argparse.py
digichem/misc/base.py
digichem/misc/io.py
digichem/misc/layered_dict.py
digichem/misc/text.py
digichem/misc/time.py
digichem/parse/__init__.py
digichem/parse/base.py
digichem/parse/cclib.py
digichem/parse/dump.py
digichem/parse/gaussian.py
digichem/parse/orca.py
digichem/parse/pyscf.py
digichem/parse/turbomole.py
digichem/parse/util.py
digichem/result/__init__.py
digichem_core-7.2.0.dist-info/METADATA
digichem_core-7.2.0.dist-info/WHEEL
digichem_core-7.2.0.dist-info/licenses/COPYING.md
digichem_core-7.2.0.dist-info/licenses/LICENSE
digichem_core-7.2.0.dist-info/RECORD
