Metadata-Version: 2.4
Name: digichem-core
Version: 7.2.0
Summary: Open-source library for Digichem core components
Project-URL: Homepage, https://github.com/Digichem-Project/digichem-core
Project-URL: Documentation, https://doc.digi-chem.co.uk
Project-URL: Issues, https://github.com/Digichem-Project/digichem-core/issues
Author-email: "Oliver S. Lee" <osl@digi-chem.ac.uk>
License: Copyright 2024 Digichem
License-File: COPYING.md
License-File: LICENSE
Classifier: License :: OSI Approved :: BSD License
Classifier: Operating System :: Unix
Classifier: Programming Language :: Python :: 3
Requires-Python: >=3.9
Requires-Dist: adjusttext
Requires-Dist: basis-set-exchange
Requires-Dist: cclib<2,>=1.7.1
Requires-Dist: colour-science
Requires-Dist: configurables
Requires-Dist: deepmerge
Requires-Dist: dill
Requires-Dist: matplotlib
Requires-Dist: openprattle
Requires-Dist: periodictable
Requires-Dist: pillow
Requires-Dist: pyyaml
Requires-Dist: rdkit
Requires-Dist: scipy
Provides-Extra: test
Requires-Dist: pyscf; extra == 'test'
Requires-Dist: pytest; extra == 'test'
Requires-Dist: pytest-lazy-fixture; extra == 'test'
